odoo/addons/website_sale_loyalty_suggestion_wizard/README.rst
odoo/addons/website_sale_loyalty_suggestion_wizard/__init__.py
odoo/addons/website_sale_loyalty_suggestion_wizard/__manifest__.py
odoo/addons/website_sale_loyalty_suggestion_wizard/controllers/__init__.py
odoo/addons/website_sale_loyalty_suggestion_wizard/controllers/main.py
odoo/addons/website_sale_loyalty_suggestion_wizard/controllers/promotion_page.py
odoo/addons/website_sale_loyalty_suggestion_wizard/controllers/promotion_wizard.py
odoo/addons/website_sale_loyalty_suggestion_wizard/i18n/es.po
odoo/addons/website_sale_loyalty_suggestion_wizard/i18n/it.po
odoo/addons/website_sale_loyalty_suggestion_wizard/i18n/website_sale_coupon_selection_wizard.pot
odoo/addons/website_sale_loyalty_suggestion_wizard/i18n/website_sale_loyalty_suggestion_wizard.pot
odoo/addons/website_sale_loyalty_suggestion_wizard/readme/CONTRIBUTORS.md
odoo/addons/website_sale_loyalty_suggestion_wizard/readme/DESCRIPTION.md
odoo/addons/website_sale_loyalty_suggestion_wizard/readme/USAGE.md
odoo/addons/website_sale_loyalty_suggestion_wizard/static/description/icon.png
odoo/addons/website_sale_loyalty_suggestion_wizard/static/description/index.html
odoo/addons/website_sale_loyalty_suggestion_wizard/static/src/js/website_sale_loyalty_suggestion_wizard.esm.js
odoo/addons/website_sale_loyalty_suggestion_wizard/static/src/js/website_sale_loyalty_suggestion_wizard_mixin.esm.js
odoo/addons/website_sale_loyalty_suggestion_wizard/static/src/scss/website_sale_loyalty_suggestion_wizard.scss
odoo/addons/website_sale_loyalty_suggestion_wizard/templates/promotion_templates.xml
odoo/addons/website_sale_loyalty_suggestion_wizard/templates/wizard_templates.xml
odoo_addon_website_sale_loyalty_suggestion_wizard-18.0.1.0.0.4.dist-info/METADATA
odoo_addon_website_sale_loyalty_suggestion_wizard-18.0.1.0.0.4.dist-info/WHEEL
odoo_addon_website_sale_loyalty_suggestion_wizard-18.0.1.0.0.4.dist-info/top_level.txt
odoo_addon_website_sale_loyalty_suggestion_wizard-18.0.1.0.0.4.dist-info/RECORD
