Metadata-Version: 2.1
Name: odoo-addon-website_sale_loyalty_suggestion_wizard
Version: 18.0.1.0.0.4
Requires-Python: >=3.10
Requires-Dist: odoo-addon-sale_loyalty_order_suggestion==18.0.*
Requires-Dist: odoo-addon-website_sale_loyalty_page==18.0.*
Requires-Dist: odoo==18.0.*
Summary: Suggests promotions and allows you to configure and apply these promotions directly from the website
Home-page: https://github.com/OCA/sale-promotion
License: AGPL-3
Author: Tecnativa, Odoo Community Association (OCA)
Author-email: support@odoo-community.org
Classifier: Programming Language :: Python
Classifier: Framework :: Odoo
Classifier: Framework :: Odoo :: 18.0
Classifier: License :: OSI Approved :: GNU Affero General Public License v3
Classifier: Development Status :: 4 - Beta
